LICENSE
README.md
setup.cfg
setup.py
datify/__init__.py
datify/datify.py
datify/deprecation_warning.py
datify.egg-info/PKG-INFO
datify.egg-info/SOURCES.txt
datify.egg-info/dependency_links.txt
datify.egg-info/top_level.txt