Metadata-Version: 2.1
Name: datify
Version: 1.1.0
Summary: An extensible library that provides the functionality of the parsing strings in different formats to extract dates.
Home-page: https://github.com/mitryp/datify
Author: Dmytro Popov
Author-email: thedmitryp@ukr.net
License: Apache-2.0
Download-URL: https://github.com/mitryp/datify/archive/refs/tags/1.1.0.tar.gz
Keywords: str,string,user-experience,user-input,date,date-strings,datify,alpha-month,month,english,russian,ukrainian,natural-language,open-source
Platform: UNKNOWN
Classifier: Development Status :: 5 - Production/Stable
Classifier: Intended Audience :: Developers
Classifier: Topic :: Software Development :: Libraries :: Python Modules
Classifier: Topic :: Text Processing
Classifier: License :: OSI Approved :: Apache Software License
Classifier: Operating System :: OS Independent
Classifier: Programming Language :: Python :: 3
Classifier: Programming Language :: Python :: 3.6
Classifier: Programming Language :: Python :: 3.7
Classifier: Programming Language :: Python :: 3.8
Classifier: Programming Language :: Python :: 3.9
Classifier: Programming Language :: Python :: 3.10
Classifier: Programming Language :: Python :: 3.11
License-File: LICENSE
